tf.py
terraformation-0.3.1.dist-info/LICENSE.txt
terraformation-0.3.1.dist-info/METADATA
terraformation-0.3.1.dist-info/WHEEL
terraformation-0.3.1.dist-info/entry_points.txt
terraformation-0.3.1.dist-info/top_level.txt
terraformation-0.3.1.dist-info/RECORD
