Metadata-Version: 2.2
Name: terraformation
Version: 0.3.1
Summary: A simple Terraform wrapper to use variable definition files if they match the workspace name.
Author-email: Nimrod Adar <nimrod@shore.co.il>
License: MIT License
Project-URL: homepage, https://git.shore.co.il/nimrod/tf
Keywords: terraform
Classifier: License :: OSI Approved :: MIT License
Classifier: Programming Language :: Python
License-File: LICENSE.txt
